contact_sam/__init__.py
contact_sam/__main__.py
contact_sam/__version__.py
contact_sam/contact_sam.py
contact_sam-0.0.1.dist-info/METADATA
contact_sam-0.0.1.dist-info/WHEEL
contact_sam-0.0.1.dist-info/top_level.txt
contact_sam-0.0.1.dist-info/RECORD
