Metadata-Version: 2.1
Name: contact_sam
Version: 0.0.1
Summary: A semi-creative excuse to make a both a python package and business cards
Home-page: https://contact-sam.github.io/contact_sam
Download-URL: https://github.com/contact-sam/contact_sam/tags
Author: Samuel Mehalko
Author-email: samuel.mehalko@ngc.com
License: GPLv3
Project-URL: Source, https://github.com/contact-sam/contact_sam
Classifier: Programming Language :: Python :: 3
Classifier: License :: OSI Approved :: GNU General Public License v3 (GPLv3)
Classifier: Operating System :: OS Independent
Classifier: Topic :: Documentation :: Sphinx
Classifier: Topic :: Office/Business
